setup.py
tsconv/__init__.py
tsconv.egg-info/PKG-INFO
tsconv.egg-info/SOURCES.txt
tsconv.egg-info/dependency_links.txt
tsconv.egg-info/entry_points.txt
tsconv.egg-info/requires.txt
tsconv.egg-info/top_level.txt